setup.py
sPyNNakerExtraModelsPlugin.egg-info/PKG-INFO
sPyNNakerExtraModelsPlugin.egg-info/SOURCES.txt
sPyNNakerExtraModelsPlugin.egg-info/dependency_links.txt
sPyNNakerExtraModelsPlugin.egg-info/requires.txt
sPyNNakerExtraModelsPlugin.egg-info/top_level.txt
spynnaker_extra_pynn_models/__init__.py
spynnaker_extra_pynn_models/model_binaries/__init__.py
spynnaker_extra_pynn_models/neural_models/__init__.py
spynnaker_extra_pynn_models/neural_models/abstract_delta_population_vertex.py
spynnaker_extra_pynn_models/neural_models/if_cond_exp_stoc.py
spynnaker_extra_pynn_models/neural_models/if_curr_delta.py
spynnaker_extra_pynn_models/neural_models/if_curr_exp_ca2_adaptive.py
spynnaker_extra_pynn_models/neural_properties/__init__.py
spynnaker_extra_pynn_models/neural_properties/synapse_dynamics/__init__.py
spynnaker_extra_pynn_models/neural_properties/synapse_dynamics/dependences/__init__.py
spynnaker_extra_pynn_models/neural_properties/synapse_dynamics/dependences/recurrent_time_dependency.py
spynnaker_extra_pynn_models/neural_properties/synapse_dynamics/dependences/vogels_2011_time_dependency.py