Metadata-Version: 1.0
Name: sPyNNakerExtraModelsPlugin
Version: 2015.003.01
Summary: Extra models not in PyNN
Home-page: https://github.com/SpiNNakerManchester/sPyNNakerExtraModelsPlugin
Author: UNKNOWN
Author-email: UNKNOWN
License: UNKNOWN
Platform: UNKNOWN
